influxtap/__init__.py
influxtap/__main__.py
influxtap/cache.py
influxtap/xdg.py
influxtap-0.1.1.dist-info/DESCRIPTION.rst
influxtap-0.1.1.dist-info/METADATA
influxtap-0.1.1.dist-info/RECORD
influxtap-0.1.1.dist-info/WHEEL
influxtap-0.1.1.dist-info/entry_points.txt
influxtap-0.1.1.dist-info/metadata.json
influxtap-0.1.1.dist-info/top_level.txt
